Day02/HalfSubtractor/sub.v
module sub(output Diff,Borr,input A,B);
assign Diff = A ^ B;
assign Borr = B & ~A;

endmodule

Day02/FullSubtractor/fs_sub.v
`include "sub.v"
module fs_sub(output Diff,Borr,input A,B,Bin);
wire W1,W2,W3;
sub SUB1(.Diff(W1),.Borr(W2),.A(A),.B(B));
sub SUB2(.Diff(Diff),.Borr(W3),.A(W1),.B(Bin));
or OR1(Borr,W2,W3);

endmodule

Day02/FullSubtractor/fs_sub_tb.v
module fs_sub_tb;
reg A,B,Bin;
wire Diff,Borr;

fs_sub INST0 (.Diff(Diff),.Borr(Borr),.A(A),.B(B),.Bin(Bin));

initial begin
   A = 0; B = 0; Bin = 0;
#1 A = 0; B = 0; Bin = 1;
#1 A = 0; B = 1; Bin = 0;
#1 A = 0; B = 1; Bin = 1;
#1 A = 1; B = 0; Bin = 0;
#1 A = 1; B = 0; Bin = 1;
#1 A = 1; B = 1; Bin = 0;
#1 A = 1; B = 1; Bin = 1;
#1 A = 0; B = 0; Bin = 0;
end

initial begin
  $monitor("%t | A = %d| B = %d|Bin = %d| Diff = %d| Borr = %d", $time, A, B, Bin, Diff, Borr);
  $dumpfile("fs_sim_tb.vcd");
  $dumpvars(0,fs_sub_tb);
end
endmodule

Day02/FullSubtractor/fs_sim_tb.vcd
$date
	Mon Oct  2 22:46:13 2023
$end
$version
	Icarus Verilog
$end
$timescale
	1s
$end
$scope module fs_sub_tb $end
$var wire 1 ! Diff $end
$var wire 1 " Borr $end
$var reg 1 # A $end
$var reg 1 $ B $end
$var reg 1 % Bin $end
$scope module INST0 $end
$var wire 1 # A $end
$var wire 1 $ B $end
$var wire 1 % Bin $end
$var wire 1 " Borr $end
$var wire 1 & W3 $end
$var wire 1 ' W2 $end
$var wire 1 ( W1 $end
$var wire 1 ! Diff $end
$scope module SUB1 $end
$var wire 1 # A $end
$var wire 1 $ B $end
$var wire 1 ' Borr $end
$var wire 1 ( Diff $end
$upscope $end
$scope module SUB2 $end
$var wire 1 ( A $end
$var wire 1 % B $end
$var wire 1 & Borr $end
$var wire 1 ! Diff $end
$upscope $end
$upscope $end
$upscope $end
$enddefinitions $end
#0
$dumpvars
0(
0'
0&
0%
0$
0#
0"
0!
$end
#1
1"
1!
1&
1%
#2
0&
1(
1'
0%
1$
#3
0!
1%
#4
0"
1!
0'
0%
0$
1#
#5
0!
1%
#6
0(
0%
1$
#7
1"
1!
1&
1%
#8
0"
0!
0&
0%
0$
0#
