Day05/seg7.v
module seg7(output reg [6:0] num, input [3:0] bcd);

always@(bcd) begin
    case(bcd)
  0 : num = 7'b1000000; // Digit 0
  1 : num = 7'b1111001; // Digit 1
  2:  num = 7'b0100100; // Digit 2
  3:  num = 7'b0110000; // Digit 3
  4:  num = 7'b0011001; // Digit 4
  5:  num = 7'b0010010; // Digit 5
  6:  num = 7'b0000010; // Digit 6
  7:  num = 7'b1111000; // Digit 7
  8:  num = 7'b0000000; // Digit 8
  9:  num = 7'b0000100; // Digit 9
  default: num = 7'b1111111;   
  endcase
end

endmodule

Day05/seg7_tb.v
module seg7_tb;

reg [3:0] bcd;
wire [6:0] num;
integer i;

seg7 INST0 (.bcd(bcd),.num(num));

//Apply inputs
initial begin
    for(i = 0;i < 10;i = i+1) 
    begin
        bcd = i; 
        #10; 
    end     
end

initial begin
  $dumpfile("seg7_sim.vcd");
  $dumpvars(0,seg7_tb);
end
      
endmodule

Day05/seg7_sim.vcd
$date
	Thu Oct  5 23:42:12 2023
$end
$version
	Icarus Verilog
$end
$timescale
	1s
$end
$scope module seg7_tb $end
$var wire 7 ! num [6:0] $end
$var reg 4 " bcd [3:0] $end
$var integer 32 # i [31:0] $end
$scope module INST0 $end
$var wire 4 $ bcd [3:0] $end
$var reg 7 % num [6:0] $end
$upscope $end
$upscope $end
$enddefinitions $end
#0
$dumpvars
b1000000 %
b0 $
b0 #
b0 "
b1000000 !
$end
#10
b1111001 !
b1111001 %
b1 "
b1 $
b1 #
#20
b100100 !
b100100 %
b10 "
b10 $
b10 #
#30
b110000 !
b110000 %
b11 "
b11 $
b11 #
#40
b11001 !
b11001 %
b100 "
b100 $
b100 #
#50
b10010 !
b10010 %
b101 "
b101 $
b101 #
#60
b10 !
b10 %
b110 "
b110 $
b110 #
#70
b1111000 !
b1111000 %
b111 "
b111 $
b111 #
#80
b0 !
b0 %
b1000 "
b1000 $
b1000 #
#90
b100 !
b100 %
b1001 "
b1001 $
b1001 #
#100
b1010 #
